slambuc/__init__.py
slambuc/__main__.py
slambuc/alg/__init__.py
slambuc/alg/util.py
slambuc/alg/app/__init__.py
slambuc/alg/app/common.py
slambuc/alg/chain/__init__.py
slambuc/alg/chain/path/__init__.py
slambuc/alg/chain/path/dp.py
slambuc/alg/chain/path/greedy.py
slambuc/alg/chain/path/min.py
slambuc/alg/chain/path/sp.py
slambuc/alg/chain/serial/__init__.py
slambuc/alg/chain/serial/greedy.py
slambuc/alg/chain/serial/ilp.py
slambuc/alg/dag/__init__.py
slambuc/alg/dag/ilp.py
slambuc/alg/ext/__init__.py
slambuc/alg/ext/baseline.py
slambuc/alg/ext/csp.py
slambuc/alg/ext/greedy.py
slambuc/alg/ext/mincut.py
slambuc/alg/tree/__init__.py
slambuc/alg/tree/layout/__init__.py
slambuc/alg/tree/layout/ilp.py
slambuc/alg/tree/parallel/__init__.py
slambuc/alg/tree/parallel/greedy.py
slambuc/alg/tree/parallel/ilp.py
slambuc/alg/tree/parallel/pseudo.py
slambuc/alg/tree/parallel/pseudo_mp.py
slambuc/alg/tree/path/__init__.py
slambuc/alg/tree/path/greedy.py
slambuc/alg/tree/path/meta.py
slambuc/alg/tree/path/min.py
slambuc/alg/tree/path/seq.py
slambuc/alg/tree/path/state.py
slambuc/alg/tree/serial/__init__.py
slambuc/alg/tree/serial/bicriteria.py
slambuc/alg/tree/serial/greedy.py
slambuc/alg/tree/serial/ilp.py
slambuc/alg/tree/serial/ilp_cplex.py
slambuc/alg/tree/serial/pseudo.py
slambuc/alg/tree/serial/pseudo_mp.py
slambuc/generator/__init__.py
slambuc/generator/transform.py
slambuc/generator/cluster/__init__.py
slambuc/generator/cluster/job_tree.py
slambuc/generator/cluster/syn_job.py
slambuc/generator/cluster/hist/cpl_hist.pkl
slambuc/generator/cluster/hist/instance_num_hist.pkl
slambuc/generator/cluster/hist/level_hist.pkl
slambuc/generator/cluster/hist/task_cpu_hist.pkl
slambuc/generator/cluster/hist/task_duration_hist.pkl
slambuc/generator/cluster/hist/task_mem_hist.pkl
slambuc/generator/cluster/hist/task_num_hist.pkl
slambuc/generator/cluster/samples/batch_task.csv
slambuc/generator/cluster/samples/sample_tasks.csv
slambuc/generator/microservice/__init__.py
slambuc-0.6.0.dist-info/licenses/LICENSE
slambuc-0.6.0.dist-info/METADATA
slambuc-0.6.0.dist-info/WHEEL
slambuc-0.6.0.dist-info/entry_points.txt
slambuc-0.6.0.dist-info/top_level.txt
slambuc-0.6.0.dist-info/RECORD
