Metadata-Version: 2.4
Name: SLAMBUC
Version: 0.6.0
Summary: Serverless Layout Adaptation with Memory-Bounds and User Constraints
Author-email: Janos Czentye <czentye@tmit.bme.hu>
License-Expression: Apache-2.0
Project-URL: Repository, https://github.com/hsnlab/SLAMBUC
Project-URL: Homepage, https://github.com/hsnlab/SLAMBUC/wiki
Project-URL: Issue Tracker, https://github.com/hsnlab/SLAMBUC/issues
Keywords: cloud,serverless,ilp,dp,tree
Classifier: Development Status :: 3 - Alpha
Classifier: Intended Audience :: Science/Research
Classifier: Operating System :: POSIX :: Linux
Classifier: Programming Language :: Python :: 3
Classifier: Programming Language :: Python :: 3.10
Classifier: Programming Language :: Python :: 3.11
Classifier: Programming Language :: Python :: 3.12
Classifier: Programming Language :: Python :: 3.13
Classifier: Programming Language :: Python :: 3.14
Classifier: Topic :: Software Development :: Libraries :: Python Modules
Requires-Python: >=3.10
License-File: LICENSE
Requires-Dist: numpy~=2.3.3
Requires-Dist: networkx~=3.5
Requires-Dist: pulp~=3.3.0
Requires-Dist: cspy>=0.1.2
Requires-Dist: click~=8.3.0
Provides-Extra: extra
Requires-Dist: pygraphviz~=1.14; extra == "extra"
Requires-Dist: matplotlib~=3.10.6; extra == "extra"
Requires-Dist: pandas~=2.3.2; extra == "extra"
Requires-Dist: scipy~=1.16.2; extra == "extra"
Requires-Dist: docplex~=2.30.251; extra == "extra"
Provides-Extra: tests
Requires-Dist: pytest~=8.4.2; extra == "tests"
Requires-Dist: tabulate~=0.9.0; extra == "tests"
Requires-Dist: twine>=6.1.0; extra == "tests"
Requires-Dist: packaging>=24.2; extra == "tests"
Provides-Extra: validation
Requires-Dist: tabulate~=0.9.0; extra == "validation"
Requires-Dist: psutil~=7.1.0; extra == "validation"
Provides-Extra: doc
Requires-Dist: pydoc-markdown~=4.8.2; extra == "doc"
Dynamic: license-file
